django_ktag-1.0.0.dist-info/DESCRIPTION.rst
django_ktag-1.0.0.dist-info/METADATA
django_ktag-1.0.0.dist-info/RECORD
django_ktag-1.0.0.dist-info/WHEEL
django_ktag-1.0.0.dist-info/metadata.json
django_ktag-1.0.0.dist-info/top_level.txt
ktag/__init__.py
ktag/admin.py
ktag/apps.py
ktag/fields.py
ktag/widgets.py
ktag/static/ktag/css/tagify.css
ktag/static/ktag/js/tagify.min.js
ktag/templates/ktag/ktag_input.html
