Metadata-Version: 2.0
Name: django-ktag
Version: 1.0.0
Summary: django tag input field 
Home-page: https://github.com/gojuukaze/django-ktag
Author: gojuukaze
Author-email: i@ikaze.uu.me
License: GUN V3.0
Platform: Any
Classifier: Development Status :: 5 - Production/Stable
Classifier: Intended Audience :: Developers
Classifier: License :: OSI Approved :: GNU General Public License v3 (GPLv3)
Classifier: Operating System :: OS Independent
Classifier: Programming Language :: Python :: 3
Classifier: Programming Language :: Python :: 3.3
Classifier: Programming Language :: Python :: 3.4
Classifier: Programming Language :: Python :: 3.5
Classifier: Programming Language :: Python :: 3.6
Classifier: Framework :: Django
Classifier: Environment :: Web Environment
Requires-Python: >=3
Requires-Dist: Django (>=2.0.0)
